jqfilters/__init__.py
jqfilters/filters.py
jqfilters/operations.py
jqfilters/value_getters.py
jqfilters-0.9.0.dist-info/LICENSE
jqfilters-0.9.0.dist-info/METADATA
jqfilters-0.9.0.dist-info/WHEEL
jqfilters-0.9.0.dist-info/top_level.txt
jqfilters-0.9.0.dist-info/RECORD
