Metadata-Version: 2.1
Name: jqfilters
Version: 0.9.0
Summary: Easy filtering based on jq syntax
Home-page: https://github.com/apastors/filters
Author: apastors
Author-email: a.pastor.sanchez@gmail.com
License: UNKNOWN
Platform: UNKNOWN
Classifier: Programming Language :: Python :: 3
Classifier: License :: OSI Approved :: MIT License
Classifier: Operating System :: OS Independent
Requires-Python: >=3.6
Requires-Dist: pyjq
